setup.py
test_sdk/__init__.py
test_sdk.egg-info/PKG-INFO
test_sdk.egg-info/SOURCES.txt
test_sdk.egg-info/dependency_links.txt
test_sdk.egg-info/top_level.txt