Metadata-Version: 1.0
Name: test-sdk
Version: 1.0.0
Summary: sdk
Home-page: UNKNOWN
Author: UNKNOWN
Author-email: UNKNOWN
License: UNKNOWN
Platform: UNKNOWN
